asset_tracking_pepsico/asset_tracking_devicelogs.py
asset_tracking_pepsico/asset_tracking_ingest.py
asset_tracking_pepsico/utilities.py
asset_tracking_pepsico/dto/PostgresSchema.py
asset_tracking_pepsico-1.0.3.dist-info/LICENSE
asset_tracking_pepsico-1.0.3.dist-info/METADATA
asset_tracking_pepsico-1.0.3.dist-info/WHEEL
asset_tracking_pepsico-1.0.3.dist-info/top_level.txt
asset_tracking_pepsico-1.0.3.dist-info/RECORD
