Metadata-Version: 2.1
Name: asset-tracking-pepsico
Version: 1.0.3
Summary: An asset tracking package where the device logs can be read and the location information can be extracted from the log file provided in the parameters.
Author-email: Jatin Talati <jatalati@in.ibm.com>
Keywords: asset,tracking,pepsico,location,latitude,longitude,store,events
Classifier: Programming Language :: Python :: 3
Classifier: Development Status :: 1 - Planning
Classifier: Operating System :: OS Independent
Requires-Python: >=3.7
License-File: LICENSE
Requires-Dist: azure-core
Requires-Dist: azure-storage-blob
Requires-Dist: toml
